randomandroidphone/README.MD
randomandroidphone/__init__.py
randomandroidphone/phonecodescountry.pkl
randomandroidphone/phoneswithtac.pkl
randomandroidphone/requirements.txt
randomandroidphone/thirdparty.json
randomandroidphone-0.10.dist-info/LICENSE.rst
randomandroidphone-0.10.dist-info/METADATA
randomandroidphone-0.10.dist-info/WHEEL
randomandroidphone-0.10.dist-info/top_level.txt
randomandroidphone-0.10.dist-info/RECORD
