Metadata-Version: 2.1
Name: randomandroidphone
Version: 0.10
Summary: Generates random data (brand, device name, imsi, imei, iccid, phone number ...) for Android cell phones
Home-page: https://github.com/hansalemaos/randomandroidphone
Author: Johannes Fischer
Author-email: aulasparticularesdealemaosp@gmail.com
License: MIT
Keywords: android
Classifier: Development Status :: 4 - Beta
Classifier: Programming Language :: Python :: 3 :: Only
Classifier: Programming Language :: Python :: 3.10
Classifier: Topic :: Software Development :: Libraries :: Python Modules
Classifier: Topic :: Utilities
License-File: LICENSE.rst
Requires-Dist: pandas
